CHANGES.rst
MANIFEST.in
README.rst
development.ini
production.ini
setup.cfg
setup.py
tilecache.cfg
papyrus_tilecache/__init__.py
papyrus_tilecache/views.py
papyrus_tilecache.egg-info/PKG-INFO
papyrus_tilecache.egg-info/SOURCES.txt
papyrus_tilecache.egg-info/dependency_links.txt
papyrus_tilecache.egg-info/entry_points.txt
papyrus_tilecache.egg-info/not-zip-safe
papyrus_tilecache.egg-info/paster_plugins.txt
papyrus_tilecache.egg-info/requires.txt
papyrus_tilecache.egg-info/top_level.txt