Metadata-Version: 1.0
Name: papyrus-tilecache
Version: 0.1
Summary: papyrus_tilecache
Home-page: http://github.com/elemoine/papyrus_tilecache
Author: Eric Lemoine
Author-email: eric.lemoine@gmail.com
License: UNKNOWN
Keywords: web geospatial papyrus tilecache pyramid pylons
Platform: UNKNOWN
Classifier: Programming Language :: Python
Classifier: Framework :: Pylons
Classifier: Topic :: Internet :: WWW/HTTP
Classifier: Topic :: Internet :: WWW/HTTP :: WSGI :: Application
